{
    "RD": {
        "A03": 1172,
        "A02": 1124,
        "A01": 1059,
        "A07": 1379,
        "A06": 1282,
        "A05": 1279,
        "A04": 1276,
        "B08": 322,
        "B09": 178,
        "B01": 1011,
        "B02": 972,
        "B03": 885,
        "B04": 737,
        "B05": 671,
        "B06": 587,
        "B07": 433,
        "A13": 1928,
        "A12": 1813,
        "A11": 1741,
        "A10": 1558,
        "A15": 2004,
        "A14": 1931,
        "B35": 811,
        "B11": 1,
        "B10": 106,
        "A09": 1509,
        "A08": 1427
    },
    "GR": {
        "E10": 1,
        "E09": 101,
        "F11": 1737,
        "E02": 858,
        "E08": 278,
        "E07": 380,
        "E06": 533,
        "E05": 625,
        "E04": 709,
        "E03": 797,
        "E01": 862,
        "F08": 1329,
        "F09": 1459,
        "F04": 1035,
        "F05": 1036,
        "F06": 1118,
        "F07": 1219,
        "F01": 877,
        "F02": 895,
        "F03": 933,
        "F10": 1596
    },
    "YL": {
        "C10": 578,
        "C12": 165,
        "C13": 109,
        "C15": 1,
        "E02": 1121,
        "C09": 704,
        "C08": 791,
        "E06": 1200,
        "E05": 1172,
        "E04": 1150,
        "E03": 1135,
        "E01": 1120,
        "C07": 838,
        "C14": 33,
        "F01": 1100,
        "F02": 1078,
        "F03": 1035
    },
    "OR": {
        "D08": 5407,
        "D09": 5696,
        "D06": 5306,
        "D07": 5330,
        "D04": 5196,
        "D05": 5200,
        "D02": 5084,
        "D03": 5138,
        "D12": 5935,
        "K02": 4440,
        "D10": 5743,
        "K04": 4364,
        "K01": 4488,
        "K07": 1822,
        "K06": 2681,
        "D11": 5827,
        "K08": 1,
        "C01": 4948,
        "C03": 4819,
        "C02": 4822,
        "C05": 4571,
        "D01": 4997,
        "C04": 4744,
        "K03": 4415,
        "D13": 6009,
        "K05": 2816
    },
    "BL": {
        "D08": 2157,
        "C10": 852,
        "C12": 493,
        "D06": 1963,
        "D07": 2012,
        "D04": 1877,
        "D05": 1880,
        "D02": 1705,
        "D03": 1824,
        "C13": 455,
        "G05": 2544,
        "G04": 2518,
        "G01": 2375,
        "G03": 2498,
        "G02": 2433,
        "C09": 909,
        "C08": 1078,
        "C01": 1560,
        "C03": 1503,
        "C02": 1506,
        "C05": 1338,
        "D01": 1607,
        "C07": 1156,
        "C06": 1265,
        "C04": 1430,
        "J03": 1,
        "J02": 244
    }
}